face_rhythm/__init__.py
face_rhythm/data_importing.py
face_rhythm/decomposition.py
face_rhythm/h5_handling.py
face_rhythm/helpers.py
face_rhythm/pipelines.py
face_rhythm/point_tracking.py
face_rhythm/project.py
face_rhythm/rois.py
face_rhythm/spectral_analysis.py
face_rhythm/util.py
face_rhythm/visualization.py
face_rhythm-0.2.5.dist-info/LICENSE
face_rhythm-0.2.5.dist-info/METADATA
face_rhythm-0.2.5.dist-info/WHEEL
face_rhythm-0.2.5.dist-info/top_level.txt
face_rhythm-0.2.5.dist-info/RECORD
