Metadata-Version: 2.1
Name: face_rhythm
Version: 0.2.5
Summary: A pipeline for analysis of facial behavior using optical flow
Home-page: https://github.com/RichieHakim/face-rhythm
Author: Rich Hakim
License: LICENSE
Keywords: neuroscience,neuroimaging,machine learning
Platform: Any
Classifier: Development Status :: 4 - Beta
Classifier: Intended Audience :: Science/Research
Classifier: Topic :: Scientific/Engineering :: Bio-Informatics
Classifier: Programming Language :: Python :: 3
License-File: LICENSE
Provides-Extra: all
Requires-Dist: numpy ==1.26.4 ; extra == 'all'
Requires-Dist: jupyter ; extra == 'all'
Requires-Dist: notebook <7 ; extra == 'all'
Requires-Dist: tensorly ==0.8.1 ; extra == 'all'
Requires-Dist: opencv-contrib-python ==4.9.0.80 ; extra == 'all'
Requires-Dist: matplotlib ; extra == 'all'
Requires-Dist: scikit-learn ==1.4.2 ; extra == 'all'
Requires-Dist: scikit-image ; extra == 'all'
Requires-Dist: pyyaml ; extra == 'all'
Requires-Dist: tqdm ; extra == 'all'
Requires-Dist: h5py ; extra == 'all'
Requires-Dist: ipywidgets ; extra == 'all'
Requires-Dist: Pillow ; extra == 'all'
Requires-Dist: eva-decord ; extra == 'all'
Requires-Dist: natsort ; extra == 'all'
Requires-Dist: pandas ; extra == 'all'
Requires-Dist: tables ; extra == 'all'
Requires-Dist: einops ; extra == 'all'
Requires-Dist: pytest ; extra == 'all'
Requires-Dist: torch ; extra == 'all'
Requires-Dist: torchvision ; extra == 'all'
Requires-Dist: torchaudio ; extra == 'all'
Requires-Dist: nvidia-ml-py3 ; extra == 'all'
Requires-Dist: py-cpuinfo ; extra == 'all'
Requires-Dist: GPUtil ; extra == 'all'
Requires-Dist: psutil ; extra == 'all'
Requires-Dist: requests ; extra == 'all'
Provides-Extra: all_cv2headless
Requires-Dist: numpy ==1.26.4 ; extra == 'all_cv2headless'
Requires-Dist: jupyter ; extra == 'all_cv2headless'
Requires-Dist: notebook <7 ; extra == 'all_cv2headless'
Requires-Dist: tensorly ==0.8.1 ; extra == 'all_cv2headless'
Requires-Dist: opencv-contrib-python-headless <=4.9.0.80 ; extra == 'all_cv2headless'
Requires-Dist: matplotlib ; extra == 'all_cv2headless'
Requires-Dist: scikit-learn ==1.4.2 ; extra == 'all_cv2headless'
Requires-Dist: scikit-image ; extra == 'all_cv2headless'
Requires-Dist: pyyaml ; extra == 'all_cv2headless'
Requires-Dist: tqdm ; extra == 'all_cv2headless'
Requires-Dist: h5py ; extra == 'all_cv2headless'
Requires-Dist: ipywidgets ; extra == 'all_cv2headless'
Requires-Dist: Pillow ; extra == 'all_cv2headless'
Requires-Dist: eva-decord ; extra == 'all_cv2headless'
Requires-Dist: natsort ; extra == 'all_cv2headless'
Requires-Dist: pandas ; extra == 'all_cv2headless'
Requires-Dist: tables ; extra == 'all_cv2headless'
Requires-Dist: einops ; extra == 'all_cv2headless'
Requires-Dist: pytest ; extra == 'all_cv2headless'
Requires-Dist: torch ; extra == 'all_cv2headless'
Requires-Dist: torchvision ; extra == 'all_cv2headless'
Requires-Dist: torchaudio ; extra == 'all_cv2headless'
Requires-Dist: nvidia-ml-py3 ; extra == 'all_cv2headless'
Requires-Dist: py-cpuinfo ; extra == 'all_cv2headless'
Requires-Dist: GPUtil ; extra == 'all_cv2headless'
Requires-Dist: psutil ; extra == 'all_cv2headless'
Requires-Dist: requests ; extra == 'all_cv2headless'
Provides-Extra: all_latest
Requires-Dist: numpy ; extra == 'all_latest'
Requires-Dist: jupyter ; extra == 'all_latest'
Requires-Dist: notebook ; extra == 'all_latest'
Requires-Dist: tensorly ; extra == 'all_latest'
Requires-Dist: opencv-contrib-python ; extra == 'all_latest'
Requires-Dist: matplotlib ; extra == 'all_latest'
Requires-Dist: scikit-learn ; extra == 'all_latest'
Requires-Dist: scikit-image ; extra == 'all_latest'
Requires-Dist: pyyaml ; extra == 'all_latest'
Requires-Dist: tqdm ; extra == 'all_latest'
Requires-Dist: h5py ; extra == 'all_latest'
Requires-Dist: ipywidgets ; extra == 'all_latest'
Requires-Dist: Pillow ; extra == 'all_latest'
Requires-Dist: eva-decord ; extra == 'all_latest'
Requires-Dist: natsort ; extra == 'all_latest'
Requires-Dist: pandas ; extra == 'all_latest'
Requires-Dist: tables ; extra == 'all_latest'
Requires-Dist: einops ; extra == 'all_latest'
Requires-Dist: pytest ; extra == 'all_latest'
Requires-Dist: torch ; extra == 'all_latest'
Requires-Dist: torchvision ; extra == 'all_latest'
Requires-Dist: torchaudio ; extra == 'all_latest'
Requires-Dist: nvidia-ml-py3 ; extra == 'all_latest'
Requires-Dist: py-cpuinfo ; extra == 'all_latest'
Requires-Dist: GPUtil ; extra == 'all_latest'
Requires-Dist: psutil ; extra == 'all_latest'
Requires-Dist: requests ; extra == 'all_latest'
Provides-Extra: all_latest_cv2headless
Requires-Dist: numpy ; extra == 'all_latest_cv2headless'
Requires-Dist: jupyter ; extra == 'all_latest_cv2headless'
Requires-Dist: notebook ; extra == 'all_latest_cv2headless'
Requires-Dist: tensorly ; extra == 'all_latest_cv2headless'
Requires-Dist: opencv-contrib-python-headless ; extra == 'all_latest_cv2headless'
Requires-Dist: matplotlib ; extra == 'all_latest_cv2headless'
Requires-Dist: scikit-learn ; extra == 'all_latest_cv2headless'
Requires-Dist: scikit-image ; extra == 'all_latest_cv2headless'
Requires-Dist: pyyaml ; extra == 'all_latest_cv2headless'
Requires-Dist: tqdm ; extra == 'all_latest_cv2headless'
Requires-Dist: h5py ; extra == 'all_latest_cv2headless'
Requires-Dist: ipywidgets ; extra == 'all_latest_cv2headless'
Requires-Dist: Pillow ; extra == 'all_latest_cv2headless'
Requires-Dist: eva-decord ; extra == 'all_latest_cv2headless'
Requires-Dist: natsort ; extra == 'all_latest_cv2headless'
Requires-Dist: pandas ; extra == 'all_latest_cv2headless'
Requires-Dist: tables ; extra == 'all_latest_cv2headless'
Requires-Dist: einops ; extra == 'all_latest_cv2headless'
Requires-Dist: pytest ; extra == 'all_latest_cv2headless'
Requires-Dist: torch ; extra == 'all_latest_cv2headless'
Requires-Dist: torchvision ; extra == 'all_latest_cv2headless'
Requires-Dist: torchaudio ; extra == 'all_latest_cv2headless'
Requires-Dist: nvidia-ml-py3 ; extra == 'all_latest_cv2headless'
Requires-Dist: py-cpuinfo ; extra == 'all_latest_cv2headless'
Requires-Dist: GPUtil ; extra == 'all_latest_cv2headless'
Requires-Dist: psutil ; extra == 'all_latest_cv2headless'
Requires-Dist: requests ; extra == 'all_latest_cv2headless'
Provides-Extra: core
Requires-Dist: numpy ==1.26.4 ; extra == 'core'
Requires-Dist: jupyter ; extra == 'core'
Requires-Dist: notebook <7 ; extra == 'core'
Requires-Dist: tensorly ==0.8.1 ; extra == 'core'
Requires-Dist: opencv-contrib-python ==4.9.0.80 ; extra == 'core'
Requires-Dist: matplotlib ; extra == 'core'
Requires-Dist: scikit-learn ==1.4.2 ; extra == 'core'
Requires-Dist: scikit-image ; extra == 'core'
Requires-Dist: pyyaml ; extra == 'core'
Requires-Dist: tqdm ; extra == 'core'
Requires-Dist: h5py ; extra == 'core'
Requires-Dist: ipywidgets ; extra == 'core'
Requires-Dist: Pillow ; extra == 'core'
Requires-Dist: eva-decord ; extra == 'core'
Requires-Dist: natsort ; extra == 'core'
Requires-Dist: pandas ; extra == 'core'
Requires-Dist: tables ; extra == 'core'
Requires-Dist: einops ; extra == 'core'
Requires-Dist: pytest ; extra == 'core'
Requires-Dist: torch ; extra == 'core'
Requires-Dist: torchvision ; extra == 'core'
Requires-Dist: torchaudio ; extra == 'core'
Requires-Dist: nvidia-ml-py3 ; extra == 'core'
Requires-Dist: py-cpuinfo ; extra == 'core'
Requires-Dist: GPUtil ; extra == 'core'
Requires-Dist: psutil ; extra == 'core'
Requires-Dist: requests ; extra == 'core'
